[
    {
        "text": "",
        "resource-id": "",
        "class": "root",
        "package": "com.twitter.android",
        "content-desc": "",
        "checkable": false,
        "checked": false,
        "clickable": false,
        "enabled": true,
        "focusable": false,
        "focused": false,
        "scrollable": false,
        "long-clickable": false,
        "password": false,
        "selected": false,
        "bounds": [
            0,
            0,
            1080,
            2214
        ],
        "id": 0,
        "children-id": [
            1,
            84
        ]
    },
    {
        "text": "",
        "resource-id": "com.twitter.android:id/root_coordinator_layout",
        "class": "android.widget.ScrollView",
        "package": "com.twitter.android",
        "content-desc": "",
        "checkable": false,
        "checked": false,
        "clickable": false,
        "enabled": true,
        "focusable": false,
        "focused": false,
        "scrollable": true,
        "long-clickable": false,
        "password": false,
        "selected": false,
        "bounds": [
            0,
            66,
            1080,
            2214
        ],
        "id": 1,
        "children-id": [
            2,
            5,
            72,
            74
        ]
    },
    {
        "text": "",
        "resource-id": "com.twitter.android:id/toolbar",
        "class": "android.view.ViewGroup",
        "package": "com.twitter.android",
        "content-desc": "",
        "checkable": false,
        "checked": false,
        "clickable": true,
        "enabled": true,
        "focusable": true,
        "focused": false,
        "scrollable": false,
        "long-clickable": false,
        "password": false,
        "selected": false,
        "bounds": [
            0,
            66,
            1080,
            220
        ],
        "id": 2,
        "children-id": [
            3,
            4
        ]
    },
    {
        "text": "",
        "resource-id": "",
        "class": "android.widget.ImageButton",
        "package": "com.twitter.android",
        "content-desc": "Show navigation drawer",
        "checkable": false,
        "checked": false,
        "clickable": true,
        "enabled": true,
        "focusable": true,
        "focused": false,
        "scrollable": false,
        "long-clickable": false,
        "password": false,
        "selected": false,
        "bounds": [
            0,
            66,
            150,
            220
        ],
        "id": 3,
        "leaf-id": 0,
        "caption": "thumbnail",
        "icon-cls": "avatar",
        "description": "Show navigation drawer"
    },
    {
        "text": "",
        "resource-id": "com.twitter.android:id/logo",
        "class": "android.widget.ImageView",
        "package": "com.twitter.android",
        "content-desc": "",
        "checkable": false,
        "checked": false,
        "clickable": true,
        "enabled": true,
        "focusable": false,
        "focused": false,
        "scrollable": false,
        "long-clickable": false,
        "password": false,
        "selected": false,
        "bounds": [
            507,
            110,
            573,
            176
        ],
        "id": 4,
        "leaf-id": 1,
        "caption": "twitter",
        "icon-cls": "twitter",
        "description": "twitter"
    },
    {
        "text": "",
        "resource-id": "com.twitter.android:id/pager",
        "class": "androidx.viewpager.widget.ViewPager",
        "package": "com.twitter.android",
        "content-desc": "",
        "checkable": false,
        "checked": false,
        "clickable": false,
        "enabled": true,
        "focusable": true,
        "focused": false,
        "scrollable": true,
        "long-clickable": false,
        "password": false,
        "selected": false,
        "bounds": [
            0,
            220,
            1080,
            2214
        ],
        "id": 5,
        "children-id": [
            6
        ]
    },
    {
        "text": "",
        "resource-id": "com.twitter.android:id/view_pager",
        "class": "androidx.viewpager.widget.ViewPager",
        "package": "com.twitter.android",
        "content-desc": "",
        "checkable": false,
        "checked": false,
        "clickable": false,
        "enabled": true,
        "focusable": true,
        "focused": false,
        "scrollable": true,
        "long-clickable": false,
        "password": false,
        "selected": false,
        "bounds": [
            0,
            220,
            1080,
            2214
        ],
        "id": 6,
        "children-id": [
            7,
            11
        ]
    },
    {
        "text": "",
        "resource-id": "com.twitter.android:id/tab_layout",
        "class": "android.widget.HorizontalScrollView",
        "package": "com.twitter.android",
        "content-desc": "",
        "checkable": false,
        "checked": false,
        "clickable": false,
        "enabled": true,
        "focusable": true,
        "focused": false,
        "scrollable": false,
        "long-clickable": false,
        "password": false,
        "selected": false,
        "bounds": [
            0,
            220,
            1080,
            352
        ],
        "id": 7,
        "children-id": [
            8,
            9
        ]
    },
    {
        "text": "For you",
        "resource-id": "",
        "class": "android.widget.TextView",
        "package": "com.twitter.android",
        "content-desc": "",
        "checkable": false,
        "checked": false,
        "clickable": false,
        "enabled": true,
        "focusable": false,
        "focused": false,
        "scrollable": false,
        "long-clickable": false,
        "password": false,
        "selected": true,
        "bounds": [
            187,
            261,
            341,
            311
        ],
        "id": 8,
        "leaf-id": 2,
        "caption": "close",
        "icon-cls": null,
        "description": "For you"
    },
    {
        "text": "",
        "resource-id": "",
        "class": "android.widget.LinearLayout",
        "package": "com.twitter.android",
        "content-desc": "Following",
        "checkable": false,
        "checked": false,
        "clickable": true,
        "enabled": true,
        "focusable": true,
        "focused": false,
        "scrollable": false,
        "long-clickable": false,
        "password": false,
        "selected": false,
        "bounds": [
            528,
            220,
            1080,
            352
        ],
        "id": 9,
        "children-id": [
            10
        ]
    },
    {
        "text": "Following",
        "resource-id": "",
        "class": "android.widget.TextView",
        "package": "com.twitter.android",
        "content-desc": "",
        "checkable": false,
        "checked": false,
        "clickable": true,
        "enabled": true,
        "focusable": false,
        "focused": false,
        "scrollable": false,
        "long-clickable": false,
        "password": false,
        "selected": false,
        "bounds": [
            715,
            261,
            893,
            311
        ],
        "id": 10,
        "leaf-id": 3,
        "caption": "<unk>",
        "icon-cls": null,
        "description": "Following"
    },
    {
        "text": "",
        "resource-id": "com.twitter.android:id/nested_coordinator_layout",
        "class": "android.widget.ScrollView",
        "package": "com.twitter.android",
        "content-desc": "",
        "checkable": false,
        "checked": false,
        "clickable": false,
        "enabled": true,
        "focusable": false,
        "focused": false,
        "scrollable": true,
        "long-clickable": false,
        "password": false,
        "selected": false,
        "bounds": [
            0,
            352,
            1080,
            2214
        ],
        "id": 11,
        "children-id": [
            12
        ]
    },
    {
        "text": "",
        "resource-id": "",
        "class": "android.view.ViewGroup",
        "package": "com.twitter.android",
        "content-desc": "",
        "checkable": false,
        "checked": false,
        "clickable": false,
        "enabled": false,
        "focusable": false,
        "focused": false,
        "scrollable": false,
        "long-clickable": false,
        "password": false,
        "selected": false,
        "bounds": [
            0,
            352,
            1080,
            2214
        ],
        "id": 12,
        "children-id": [
            13
        ]
    },
    {
        "text": "",
        "resource-id": "android:id/list",
        "class": "androidx.recyclerview.widget.RecyclerView",
        "package": "com.twitter.android",
        "content-desc": "Home timeline list",
        "checkable": false,
        "checked": false,
        "clickable": false,
        "enabled": true,
        "focusable": true,
        "focused": false,
        "scrollable": true,
        "long-clickable": false,
        "password": false,
        "selected": false,
        "bounds": [
            0,
            352,
            1080,
            2214
        ],
        "id": 13,
        "children-id": [
            14,
            17,
            58
        ]
    },
    {
        "text": "",
        "resource-id": "",
        "class": "android.view.ViewGroup",
        "package": "com.twitter.android",
        "content-desc": "",
        "checkable": false,
        "checked": false,
        "clickable": true,
        "enabled": true,
        "focusable": true,
        "focused": false,
        "scrollable": false,
        "long-clickable": true,
        "password": false,
        "selected": false,
        "bounds": [
            0,
            352,
            1080,
            407
        ],
        "id": 14,
        "children-id": [
            15
        ]
    },
    {
        "text": "",
        "resource-id": "com.twitter.android:id/row",
        "class": "android.view.ViewGroup",
        "package": "com.twitter.android",
        "content-desc": "Syngenta ANZ @SyngentaANZ.    LET'S CATCH A CEREAL KILLER BEFORE IT'S TOO LATE.\nYou've made it through Harvest. Now is the time to test, plan ahead and manage your crown rot risk for 2023..   Video. Learn more and register for a free PREDICTA* B test kit today. . syngenta.com.au. .          Promoted.  feb 07.  1 reply.  2 retweets.  7 likes.  146079 verified views. ",
        "checkable": false,
        "checked": false,
        "clickable": true,
        "enabled": true,
        "focusable": false,
        "focused": false,
        "scrollable": false,
        "long-clickable": false,
        "password": false,
        "selected": false,
        "bounds": [
            0,
            352,
            1080,
            406
        ],
        "id": 15,
        "children-id": [
            16
        ]
    },
    {
        "text": "Promoted",
        "resource-id": "com.twitter.android:id/tweet_promoted_badge_bottom",
        "class": "android.widget.TextView",
        "package": "com.twitter.android",
        "content-desc": "",
        "checkable": false,
        "checked": false,
        "clickable": true,
        "enabled": true,
        "focusable": false,
        "focused": false,
        "scrollable": false,
        "long-clickable": false,
        "password": false,
        "selected": false,
        "bounds": [
            210,
            352,
            1047,
            373
        ],
        "id": 16,
        "leaf-id": 4,
        "caption": "minimize map",
        "icon-cls": null,
        "description": "Promoted"
    },
    {
        "text": "",
        "resource-id": "",
        "class": "android.view.ViewGroup",
        "package": "com.twitter.android",
        "content-desc": "",
        "checkable": false,
        "checked": false,
        "clickable": true,
        "enabled": true,
        "focusable": true,
        "focused": false,
        "scrollable": false,
        "long-clickable": true,
        "password": false,
        "selected": false,
        "bounds": [
            0,
            407,
            1080,
            1694
        ],
        "id": 17,
        "children-id": [
            18
        ]
    },
    {
        "text": "",
        "resource-id": "com.twitter.android:id/row",
        "class": "android.view.ViewGroup",
        "package": "com.twitter.android",
        "content-desc": "Barstool Sports @barstoolsports Verified Business.    Should you always tip your DoorDash/UberEats drivers?.        Tweet from topic \"Barstool Sports\".      6 days ago.  5538 replies.  2210 retweets.  18456 likes.  15651286 verified views. ",
        "checkable": false,
        "checked": false,
        "clickable": true,
        "enabled": true,
        "focusable": false,
        "focused": false,
        "scrollable": false,
        "long-clickable": false,
        "password": false,
        "selected": false,
        "bounds": [
            0,
            407,
            1080,
            1693
        ],
        "id": 18,
        "children-id": [
            19,
            20,
            25,
            27,
            28,
            29,
            31,
            38,
            39,
            40,
            43
        ]
    },
    {
        "text": "",
        "resource-id": "com.twitter.android:id/social_context_badge",
        "class": "android.widget.ImageView",
        "package": "com.twitter.android",
        "content-desc": "",
        "checkable": false,
        "checked": false,
        "clickable": true,
        "enabled": true,
        "focusable": false,
        "focused": false,
        "scrollable": false,
        "long-clickable": false,
        "password": false,
        "selected": false,
        "bounds": [
            138,
            435,
            182,
            479
        ],
        "id": 19,
        "leaf-id": 5,
        "caption": "select final point",
        "icon-cls": null,
        "description": "select final point"
    },
    {
        "text": "",
        "resource-id": "com.twitter.android:id/tweet_social_context",
        "class": "android.view.ViewGroup",
        "package": "com.twitter.android",
        "content-desc": "",
        "checkable": false,
        "checked": false,
        "clickable": true,
        "enabled": true,
        "focusable": false,
        "focused": false,
        "scrollable": false,
        "long-clickable": false,
        "password": false,
        "selected": false,
        "bounds": [
            210,
            407,
            1080,
            490
        ],
        "id": 20,
        "children-id": [
            21,
            22,
            23,
            24
        ]
    },
    {
        "text": "Barstool Sports",
        "resource-id": "com.twitter.android:id/social_context_text",
        "class": "android.widget.TextView",
        "package": "com.twitter.android",
        "content-desc": "",
        "checkable": false,
        "checked": false,
        "clickable": true,
        "enabled": true,
        "focusable": true,
        "focused": false,
        "scrollable": false,
        "long-clickable": false,
        "password": false,
        "selected": false,
        "bounds": [
            210,
            407,
            474,
            484
        ],
        "id": 21,
        "leaf-id": 6,
        "caption": "default",
        "icon-cls": null,
        "description": "Barstool Sports"
    },
    {
        "text": "",
        "resource-id": "com.twitter.android:id/social_context_dot_divider",
        "class": "android.widget.ImageView",
        "package": "com.twitter.android",
        "content-desc": "",
        "checkable": false,
        "checked": false,
        "clickable": true,
        "enabled": true,
        "focusable": false,
        "focused": false,
        "scrollable": false,
        "long-clickable": false,
        "password": false,
        "selected": false,
        "bounds": [
            474,
            407,
            502,
            484
        ],
        "id": 22,
        "leaf-id": 7,
        "caption": "like tweet",
        "icon-cls": null,
        "description": "like tweet"
    },
    {
        "text": "Follow Topic",
        "resource-id": "com.twitter.android:id/social_context_button",
        "class": "android.widget.TextView",
        "package": "com.twitter.android",
        "content-desc": "",
        "checkable": false,
        "checked": false,
        "clickable": true,
        "enabled": true,
        "focusable": true,
        "focused": false,
        "scrollable": false,
        "long-clickable": false,
        "password": false,
        "selected": false,
        "bounds": [
            502,
            407,
            714,
            484
        ],
        "id": 23,
        "leaf-id": 8,
        "caption": "<unk>",
        "icon-cls": null,
        "description": "Follow Topic"
    },
    {
        "NAF": true,
        "text": "",
        "resource-id": "com.twitter.android:id/social_context_curation_action",
        "class": "android.widget.ImageView",
        "package": "com.twitter.android",
        "content-desc": "",
        "checkable": false,
        "checked": false,
        "clickable": true,
        "enabled": true,
        "focusable": true,
        "focused": false,
        "scrollable": false,
        "long-clickable": false,
        "password": false,
        "selected": false,
        "bounds": [
            981,
            407,
            1069,
            490
        ],
        "id": 24,
        "leaf-id": 9,
        "caption": "close tab",
        "icon-cls": "close",
        "description": "close"
    },
    {
        "text": "",
        "resource-id": "com.twitter.android:id/tweet_profile_image",
        "class": "android.widget.FrameLayout",
        "package": "com.twitter.android",
        "content-desc": "Profile image",
        "checkable": false,
        "checked": false,
        "clickable": true,
        "enabled": true,
        "focusable": true,
        "focused": false,
        "scrollable": false,
        "long-clickable": false,
        "password": false,
        "selected": false,
        "bounds": [
            33,
            512,
            182,
            661
        ],
        "id": 25,
        "children-id": [
            26
        ]
    },
    {
        "text": "",
        "resource-id": "",
        "class": "android.widget.ImageView",
        "package": "com.twitter.android",
        "content-desc": "",
        "checkable": false,
        "checked": false,
        "clickable": true,
        "enabled": true,
        "focusable": false,
        "focused": false,
        "scrollable": false,
        "long-clickable": false,
        "password": false,
        "selected": false,
        "bounds": [
            33,
            512,
            182,
            661
        ],
        "id": 26,
        "leaf-id": 10,
        "caption": "<unk>",
        "icon-cls": null,
        "description": null
    },
    {
        "text": "",
        "resource-id": "com.twitter.android:id/tweet_header",
        "class": "android.view.ViewGroup",
        "package": "com.twitter.android",
        "content-desc": "",
        "checkable": false,
        "checked": false,
        "clickable": true,
        "enabled": true,
        "focusable": false,
        "focused": false,
        "scrollable": false,
        "long-clickable": false,
        "password": false,
        "selected": false,
        "bounds": [
            210,
            512,
            981,
            551
        ],
        "id": 27,
        "leaf-id": 11,
        "caption": "<unk>",
        "icon-cls": null,
        "description": null
    },
    {
        "NAF": true,
        "text": "",
        "resource-id": "com.twitter.android:id/tweet_curation_action",
        "class": "android.widget.ImageView",
        "package": "com.twitter.android",
        "content-desc": "",
        "checkable": false,
        "checked": false,
        "clickable": true,
        "enabled": true,
        "focusable": true,
        "focused": false,
        "scrollable": false,
        "long-clickable": false,
        "password": false,
        "selected": false,
        "bounds": [
            981,
            482,
            1069,
            570
        ],
        "id": 28,
        "leaf-id": 12,
        "caption": "more options",
        "icon-cls": "more",
        "description": "more"
    },
    {
        "text": "",
        "resource-id": "com.twitter.android:id/tweet_content_text",
        "class": "android.view.View",
        "package": "com.twitter.android",
        "content-desc": "",
        "checkable": false,
        "checked": false,
        "clickable": true,
        "enabled": true,
        "focusable": true,
        "focused": false,
        "scrollable": false,
        "long-clickable": false,
        "password": false,
        "selected": false,
        "bounds": [
            210,
            557,
            1047,
            661
        ],
        "id": 29,
        "children-id": [
            30
        ]
    },
    {
        "text": "Should you always tip your DoorDash/UberEats drivers?",
        "resource-id": "",
        "class": "android.view.View",
        "package": "com.twitter.android",
        "content-desc": "",
        "checkable": false,
        "checked": false,
        "clickable": true,
        "enabled": true,
        "focusable": true,
        "focused": false,
        "scrollable": false,
        "long-clickable": false,
        "password": false,
        "selected": false,
        "bounds": [
            210,
            557,
            1047,
            661
        ],
        "id": 30,
        "leaf-id": 13,
        "caption": "<unk> <unk> <unk> <unk> <unk> <unk> <unk> <unk> <unk> <unk> <unk> <unk> <unk> <unk>",
        "icon-cls": null,
        "description": "Should you always tip your DoorDash/UberEats drivers?"
    },
    {
        "text": "",
        "resource-id": "com.twitter.android:id/player",
        "class": "android.widget.FrameLayout",
        "package": "com.twitter.android",
        "content-desc": "",
        "checkable": false,
        "checked": false,
        "clickable": true,
        "enabled": true,
        "focusable": true,
        "focused": false,
        "scrollable": false,
        "long-clickable": false,
        "password": false,
        "selected": false,
        "bounds": [
            210,
            680,
            1047,
            1517
        ],
        "id": 31,
        "children-id": [
            32,
            34
        ]
    },
    {
        "text": "",
        "resource-id": "",
        "class": "android.view.ViewGroup",
        "package": "com.twitter.android",
        "content-desc": "",
        "checkable": false,
        "checked": false,
        "clickable": true,
        "enabled": true,
        "focusable": false,
        "focused": false,
        "scrollable": false,
        "long-clickable": false,
        "password": false,
        "selected": false,
        "bounds": [
            210,
            680,
            1047,
            1517
        ],
        "id": 32,
        "children-id": [
            33
        ]
    },
    {
        "text": "",
        "resource-id": "",
        "class": "ddw",
        "package": "com.twitter.android",
        "content-desc": "",
        "checkable": false,
        "checked": false,
        "clickable": true,
        "enabled": true,
        "focusable": false,
        "focused": false,
        "scrollable": false,
        "long-clickable": false,
        "password": false,
        "selected": false,
        "bounds": [
            210,
            680,
            1047,
            1517
        ],
        "id": 33,
        "leaf-id": 14,
        "caption": "dd news",
        "icon-cls": null,
        "description": "dd news"
    },
    {
        "text": "",
        "resource-id": "",
        "class": "android.view.ViewGroup",
        "package": "com.twitter.android",
        "content-desc": "",
        "checkable": false,
        "checked": false,
        "clickable": true,
        "enabled": true,
        "focusable": false,
        "focused": false,
        "scrollable": false,
        "long-clickable": false,
        "password": false,
        "selected": false,
        "bounds": [
            210,
            680,
            1047,
            1517
        ],
        "id": 34,
        "children-id": [
            35,
            36
        ]
    },
    {
        "text": "",
        "resource-id": "",
        "class": "android.view.View",
        "package": "com.twitter.android",
        "content-desc": "",
        "checkable": false,
        "checked": false,
        "clickable": true,
        "enabled": true,
        "focusable": false,
        "focused": false,
        "scrollable": false,
        "long-clickable": false,
        "password": false,
        "selected": false,
        "bounds": [
            254,
            724,
            1003,
            1473
        ],
        "id": 35,
        "leaf-id": 15,
        "caption": "thumbnail",
        "icon-cls": null,
        "description": "thumbnail"
    },
    {
        "text": "",
        "resource-id": "com.twitter.android:id/audio_toggle_view",
        "class": "android.widget.FrameLayout",
        "package": "com.twitter.android",
        "content-desc": "",
        "checkable": false,
        "checked": false,
        "clickable": true,
        "enabled": true,
        "focusable": true,
        "focused": false,
        "scrollable": false,
        "long-clickable": false,
        "password": false,
        "selected": false,
        "bounds": [
            942,
            1423,
            1014,
            1495
        ],
        "id": 36,
        "children-id": [
            37
        ]
    },
    {
        "text": "",
        "resource-id": "com.twitter.android:id/audio_toggle_icon",
        "class": "android.widget.ImageView",
        "package": "com.twitter.android",
        "content-desc": "Unmute audio",
        "checkable": false,
        "checked": false,
        "clickable": true,
        "enabled": true,
        "focusable": false,
        "focused": false,
        "scrollable": false,
        "long-clickable": false,
        "password": false,
        "selected": false,
        "bounds": [
            959,
            1440,
            997,
            1478
        ],
        "id": 37,
        "leaf-id": 16,
        "caption": "change <unk>",
        "icon-cls": null,
        "description": "Unmute audio"
    },
    {
        "text": "6.2M views",
        "resource-id": "com.twitter.android:id/view_counts",
        "class": "android.widget.TextView",
        "package": "com.twitter.android",
        "content-desc": "",
        "checkable": false,
        "checked": false,
        "clickable": true,
        "enabled": true,
        "focusable": false,
        "focused": false,
        "scrollable": false,
        "long-clickable": false,
        "password": false,
        "selected": false,
        "bounds": [
            210,
            1539,
            392,
            1583
        ],
        "id": 38,
        "leaf-id": 17,
        "caption": "<unk>",
        "icon-cls": null,
        "description": "6.2M views"
    },
    {
        "text": "\u2022",
        "resource-id": "com.twitter.android:id/divider_interpunct",
        "class": "android.widget.TextView",
        "package": "com.twitter.android",
        "content-desc": "",
        "checkable": false,
        "checked": false,
        "clickable": true,
        "enabled": true,
        "focusable": false,
        "focused": false,
        "scrollable": false,
        "long-clickable": false,
        "password": false,
        "selected": false,
        "bounds": [
            392,
            1539,
            429,
            1583
        ],
        "id": 39,
        "leaf-id": 18,
        "caption": "more",
        "icon-cls": null,
        "description": "\u2022"
    },
    {
        "text": "",
        "resource-id": "com.twitter.android:id/site_user",
        "class": "android.widget.RelativeLayout",
        "package": "com.twitter.android",
        "content-desc": "",
        "checkable": false,
        "checked": false,
        "clickable": true,
        "enabled": true,
        "focusable": true,
        "focused": false,
        "scrollable": false,
        "long-clickable": false,
        "password": false,
        "selected": false,
        "bounds": [
            429,
            1539,
            999,
            1583
        ],
        "id": 40,
        "children-id": [
            41,
            42
        ]
    },
    {
        "text": "From",
        "resource-id": "com.twitter.android:id/default_text",
        "class": "android.widget.TextView",
        "package": "com.twitter.android",
        "content-desc": "",
        "checkable": false,
        "checked": false,
        "clickable": true,
        "enabled": true,
        "focusable": false,
        "focused": false,
        "scrollable": false,
        "long-clickable": false,
        "password": false,
        "selected": false,
        "bounds": [
            432,
            1539,
            514,
            1583
        ],
        "id": 41,
        "leaf-id": 19,
        "caption": "choose stream",
        "icon-cls": null,
        "description": "From"
    },
    {
        "text": "Raphouse TV (RHTV) Backup",
        "resource-id": "com.twitter.android:id/screenname_item",
        "class": "android.widget.TextView",
        "package": "com.twitter.android",
        "content-desc": "",
        "checkable": false,
        "checked": false,
        "clickable": true,
        "enabled": true,
        "focusable": false,
        "focused": false,
        "scrollable": false,
        "long-clickable": false,
        "password": false,
        "selected": false,
        "bounds": [
            525,
            1539,
            996,
            1583
        ],
        "id": 42,
        "leaf-id": 20,
        "caption": "<unk> wifi",
        "icon-cls": "date_range",
        "description": "Raphouse TV (RHTV) Backup"
    },
    {
        "text": "",
        "resource-id": "",
        "class": "android.view.ViewGroup",
        "package": "com.twitter.android",
        "content-desc": "",
        "checkable": false,
        "checked": false,
        "clickable": true,
        "enabled": true,
        "focusable": false,
        "focused": false,
        "scrollable": false,
        "long-clickable": false,
        "password": false,
        "selected": false,
        "bounds": [
            182,
            1583,
            1047,
            1693
        ],
        "id": 43,
        "children-id": [
            44,
            47,
            50,
            53,
            56
        ]
    },
    {
        "text": "",
        "resource-id": "com.twitter.android:id/inline_reply",
        "class": "android.view.ViewGroup",
        "package": "com.twitter.android",
        "content-desc": "",
        "checkable": false,
        "checked": false,
        "clickable": true,
        "enabled": true,
        "focusable": true,
        "focused": false,
        "scrollable": false,
        "long-clickable": false,
        "password": false,
        "selected": false,
        "bounds": [
            182,
            1583,
            370,
            1693
        ],
        "id": 44,
        "children-id": [
            45,
            46
        ]
    },
    {
        "text": "",
        "resource-id": "com.twitter.android:id/inline_action_item_icon",
        "class": "android.widget.ImageView",
        "package": "com.twitter.android",
        "content-desc": "",
        "checkable": false,
        "checked": false,
        "clickable": true,
        "enabled": true,
        "focusable": false,
        "focused": false,
        "scrollable": false,
        "long-clickable": false,
        "password": false,
        "selected": false,
        "bounds": [
            212,
            1613,
            262,
            1663
        ],
        "id": 45,
        "leaf-id": 21,
        "caption": "<unk>",
        "icon-cls": "chat",
        "description": "chat"
    },
    {
        "text": "5,538",
        "resource-id": "",
        "class": "android.widget.TextView",
        "package": "com.twitter.android",
        "content-desc": "",
        "checkable": false,
        "checked": false,
        "clickable": true,
        "enabled": true,
        "focusable": false,
        "focused": false,
        "scrollable": false,
        "long-clickable": false,
        "password": false,
        "selected": false,
        "bounds": [
            268,
            1616,
            363,
            1659
        ],
        "id": 46,
        "leaf-id": 22,
        "caption": "menu",
        "icon-cls": null,
        "description": "5,538"
    },
    {
        "text": "",
        "resource-id": "com.twitter.android:id/inline_retweet",
        "class": "android.view.ViewGroup",
        "package": "com.twitter.android",
        "content-desc": "",
        "checkable": false,
        "checked": false,
        "clickable": true,
        "enabled": true,
        "focusable": true,
        "focused": false,
        "scrollable": false,
        "long-clickable": false,
        "password": false,
        "selected": false,
        "bounds": [
            370,
            1583,
            558,
            1693
        ],
        "id": 47,
        "children-id": [
            48,
            49
        ]
    },
    {
        "text": "",
        "resource-id": "com.twitter.android:id/inline_action_item_icon",
        "class": "android.widget.ImageView",
        "package": "com.twitter.android",
        "content-desc": "",
        "checkable": false,
        "checked": false,
        "clickable": true,
        "enabled": true,
        "focusable": false,
        "focused": false,
        "scrollable": false,
        "long-clickable": false,
        "password": false,
        "selected": false,
        "bounds": [
            400,
            1613,
            450,
            1663
        ],
        "id": 48,
        "leaf-id": 23,
        "caption": "switch direction",
        "icon-cls": null,
        "description": "switch direction"
    },
    {
        "text": "2,210",
        "resource-id": "",
        "class": "android.widget.TextView",
        "package": "com.twitter.android",
        "content-desc": "",
        "checkable": false,
        "checked": false,
        "clickable": true,
        "enabled": true,
        "focusable": false,
        "focused": false,
        "scrollable": false,
        "long-clickable": false,
        "password": false,
        "selected": false,
        "bounds": [
            456,
            1616,
            546,
            1659
        ],
        "id": 49,
        "leaf-id": 24,
        "caption": "choose stream",
        "icon-cls": null,
        "description": "2,210"
    },
    {
        "text": "",
        "resource-id": "com.twitter.android:id/inline_like",
        "class": "android.view.ViewGroup",
        "package": "com.twitter.android",
        "content-desc": "",
        "checkable": false,
        "checked": false,
        "clickable": true,
        "enabled": true,
        "focusable": true,
        "focused": false,
        "scrollable": false,
        "long-clickable": false,
        "password": false,
        "selected": false,
        "bounds": [
            558,
            1583,
            746,
            1693
        ],
        "id": 50,
        "children-id": [
            51,
            52
        ]
    },
    {
        "text": "",
        "resource-id": "com.twitter.android:id/inline_action_item_icon",
        "class": "android.widget.ImageView",
        "package": "com.twitter.android",
        "content-desc": "",
        "checkable": false,
        "checked": false,
        "clickable": true,
        "enabled": true,
        "focusable": false,
        "focused": false,
        "scrollable": false,
        "long-clickable": false,
        "password": false,
        "selected": false,
        "bounds": [
            588,
            1613,
            638,
            1663
        ],
        "id": 51,
        "leaf-id": 25,
        "caption": "add to favorites",
        "icon-cls": "favorite",
        "description": "favorite"
    },
    {
        "text": "18.4K",
        "resource-id": "",
        "class": "android.widget.TextView",
        "package": "com.twitter.android",
        "content-desc": "",
        "checkable": false,
        "checked": false,
        "clickable": true,
        "enabled": true,
        "focusable": false,
        "focused": false,
        "scrollable": false,
        "long-clickable": false,
        "password": false,
        "selected": false,
        "bounds": [
            644,
            1616,
            733,
            1659
        ],
        "id": 52,
        "leaf-id": 26,
        "caption": "choose",
        "icon-cls": null,
        "description": "18.4K"
    },
    {
        "text": "",
        "resource-id": "com.twitter.android:id/inline_view_count",
        "class": "android.view.ViewGroup",
        "package": "com.twitter.android",
        "content-desc": "",
        "checkable": false,
        "checked": false,
        "clickable": true,
        "enabled": true,
        "focusable": true,
        "focused": false,
        "scrollable": false,
        "long-clickable": false,
        "password": false,
        "selected": false,
        "bounds": [
            746,
            1583,
            934,
            1693
        ],
        "id": 53,
        "children-id": [
            54,
            55
        ]
    },
    {
        "text": "",
        "resource-id": "com.twitter.android:id/inline_action_item_icon",
        "class": "android.widget.ImageView",
        "package": "com.twitter.android",
        "content-desc": "",
        "checkable": false,
        "checked": false,
        "clickable": true,
        "enabled": true,
        "focusable": false,
        "focused": false,
        "scrollable": false,
        "long-clickable": false,
        "password": false,
        "selected": false,
        "bounds": [
            776,
            1613,
            826,
            1663
        ],
        "id": 54,
        "leaf-id": 27,
        "caption": "settings",
        "icon-cls": null,
        "description": "settings"
    },
    {
        "text": "15.6M",
        "resource-id": "",
        "class": "android.widget.TextView",
        "package": "com.twitter.android",
        "content-desc": "",
        "checkable": false,
        "checked": false,
        "clickable": true,
        "enabled": true,
        "focusable": false,
        "focused": false,
        "scrollable": false,
        "long-clickable": false,
        "password": false,
        "selected": false,
        "bounds": [
            832,
            1616,
            929,
            1659
        ],
        "id": 55,
        "leaf-id": 28,
        "caption": "choose stream",
        "icon-cls": null,
        "description": "15.6M"
    },
    {
        "NAF": true,
        "text": "",
        "resource-id": "com.twitter.android:id/inline_twitter_share",
        "class": "android.view.ViewGroup",
        "package": "com.twitter.android",
        "content-desc": "",
        "checkable": false,
        "checked": false,
        "clickable": true,
        "enabled": true,
        "focusable": true,
        "focused": false,
        "scrollable": false,
        "long-clickable": false,
        "password": false,
        "selected": false,
        "bounds": [
            934,
            1583,
            1047,
            1693
        ],
        "id": 56,
        "children-id": [
            57
        ]
    },
    {
        "text": "",
        "resource-id": "com.twitter.android:id/inline_action_item_icon",
        "class": "android.widget.ImageView",
        "package": "com.twitter.android",
        "content-desc": "",
        "checkable": false,
        "checked": false,
        "clickable": true,
        "enabled": true,
        "focusable": false,
        "focused": false,
        "scrollable": false,
        "long-clickable": false,
        "password": false,
        "selected": false,
        "bounds": [
            964,
            1613,
            1014,
            1663
        ],
        "id": 57,
        "leaf-id": 29,
        "caption": "search",
        "icon-cls": "share",
        "description": "share"
    },
    {
        "text": "",
        "resource-id": "",
        "class": "android.view.ViewGroup",
        "package": "com.twitter.android",
        "content-desc": "",
        "checkable": false,
        "checked": false,
        "clickable": true,
        "enabled": true,
        "focusable": true,
        "focused": false,
        "scrollable": false,
        "long-clickable": true,
        "password": false,
        "selected": false,
        "bounds": [
            0,
            1694,
            1080,
            2214
        ],
        "id": 58,
        "children-id": [
            59
        ]
    },
    {
        "text": "",
        "resource-id": "com.twitter.android:id/row",
        "class": "android.view.ViewGroup",
        "package": "com.twitter.android",
        "content-desc": "Dillon Loomis @DillonLoomis22 Verified.    The 3 camps after $TSLA Investor Day\n\n1) asleep, not interested in engineering or the mission, just here for products and/or ST stock moves\n\n2) most of Wall St. - realizing they have no idea how to model any of what was just said, internally questioning career adequacy\n\n3)\u2026.        Tweet from topic \"$TSLA\".      5 days ago.  407 replies.  162 retweets.  1823 likes.  265261 verified views. ",
        "checkable": false,
        "checked": false,
        "clickable": true,
        "enabled": true,
        "focusable": false,
        "focused": false,
        "scrollable": false,
        "long-clickable": false,
        "password": false,
        "selected": false,
        "bounds": [
            0,
            1694,
            1080,
            2214
        ],
        "id": 59,
        "children-id": [
            60,
            61,
            66,
            68,
            69,
            70
        ]
    },
    {
        "text": "",
        "resource-id": "com.twitter.android:id/social_context_badge",
        "class": "android.widget.ImageView",
        "package": "com.twitter.android",
        "content-desc": "",
        "checkable": false,
        "checked": false,
        "clickable": true,
        "enabled": true,
        "focusable": false,
        "focused": false,
        "scrollable": false,
        "long-clickable": false,
        "password": false,
        "selected": false,
        "bounds": [
            138,
            1722,
            182,
            1766
        ],
        "id": 60,
        "leaf-id": 30,
        "caption": "select final point",
        "icon-cls": null,
        "description": "select final point"
    },
    {
        "text": "",
        "resource-id": "com.twitter.android:id/tweet_social_context",
        "class": "android.view.ViewGroup",
        "package": "com.twitter.android",
        "content-desc": "",
        "checkable": false,
        "checked": false,
        "clickable": true,
        "enabled": true,
        "focusable": false,
        "focused": false,
        "scrollable": false,
        "long-clickable": false,
        "password": false,
        "selected": false,
        "bounds": [
            210,
            1694,
            1080,
            1777
        ],
        "id": 61,
        "children-id": [
            62,
            63,
            64,
            65
        ]
    },
    {
        "text": "$TSLA",
        "resource-id": "com.twitter.android:id/social_context_text",
        "class": "android.widget.TextView",
        "package": "com.twitter.android",
        "content-desc": "",
        "checkable": false,
        "checked": false,
        "clickable": true,
        "enabled": true,
        "focusable": true,
        "focused": false,
        "scrollable": false,
        "long-clickable": false,
        "password": false,
        "selected": false,
        "bounds": [
            210,
            1694,
            323,
            1771
        ],
        "id": 62,
        "leaf-id": 31,
        "caption": "narando",
        "icon-cls": null,
        "description": "$TSLA"
    },
    {
        "text": "",
        "resource-id": "com.twitter.android:id/social_context_dot_divider",
        "class": "android.widget.ImageView",
        "package": "com.twitter.android",
        "content-desc": "",
        "checkable": false,
        "checked": false,
        "clickable": true,
        "enabled": true,
        "focusable": false,
        "focused": false,
        "scrollable": false,
        "long-clickable": false,
        "password": false,
        "selected": false,
        "bounds": [
            323,
            1694,
            351,
            1771
        ],
        "id": 63,
        "leaf-id": 32,
        "caption": "like tweet",
        "icon-cls": null,
        "description": "like tweet"
    },
    {
        "text": "Follow Topic",
        "resource-id": "com.twitter.android:id/social_context_button",
        "class": "android.widget.TextView",
        "package": "com.twitter.android",
        "content-desc": "",
        "checkable": false,
        "checked": false,
        "clickable": true,
        "enabled": true,
        "focusable": true,
        "focused": false,
        "scrollable": false,
        "long-clickable": false,
        "password": false,
        "selected": false,
        "bounds": [
            351,
            1694,
            563,
            1771
        ],
        "id": 64,
        "leaf-id": 33,
        "caption": "<unk>",
        "icon-cls": null,
        "description": "Follow Topic"
    },
    {
        "NAF": true,
        "text": "",
        "resource-id": "com.twitter.android:id/social_context_curation_action",
        "class": "android.widget.ImageView",
        "package": "com.twitter.android",
        "content-desc": "",
        "checkable": false,
        "checked": false,
        "clickable": true,
        "enabled": true,
        "focusable": true,
        "focused": false,
        "scrollable": false,
        "long-clickable": false,
        "password": false,
        "selected": false,
        "bounds": [
            981,
            1694,
            1069,
            1777
        ],
        "id": 65,
        "leaf-id": 34,
        "caption": "close tab",
        "icon-cls": "close",
        "description": "close"
    },
    {
        "text": "",
        "resource-id": "com.twitter.android:id/tweet_profile_image",
        "class": "android.widget.FrameLayout",
        "package": "com.twitter.android",
        "content-desc": "Profile image",
        "checkable": false,
        "checked": false,
        "clickable": true,
        "enabled": true,
        "focusable": true,
        "focused": false,
        "scrollable": false,
        "long-clickable": false,
        "password": false,
        "selected": false,
        "bounds": [
            33,
            1799,
            182,
            1948
        ],
        "id": 66,
        "children-id": [
            67
        ]
    },
    {
        "text": "",
        "resource-id": "",
        "class": "android.widget.ImageView",
        "package": "com.twitter.android",
        "content-desc": "",
        "checkable": false,
        "checked": false,
        "clickable": true,
        "enabled": true,
        "focusable": false,
        "focused": false,
        "scrollable": false,
        "long-clickable": false,
        "password": false,
        "selected": false,
        "bounds": [
            33,
            1799,
            182,
            1948
        ],
        "id": 67,
        "leaf-id": 35,
        "caption": "profile photo",
        "icon-cls": "avatar",
        "description": "avatar"
    },
    {
        "text": "",
        "resource-id": "com.twitter.android:id/tweet_header",
        "class": "android.view.ViewGroup",
        "package": "com.twitter.android",
        "content-desc": "",
        "checkable": false,
        "checked": false,
        "clickable": true,
        "enabled": true,
        "focusable": false,
        "focused": false,
        "scrollable": false,
        "long-clickable": false,
        "password": false,
        "selected": false,
        "bounds": [
            210,
            1799,
            981,
            1840
        ],
        "id": 68,
        "leaf-id": 36,
        "caption": "<unk> <unk>",
        "icon-cls": null,
        "description": null
    },
    {
        "NAF": true,
        "text": "",
        "resource-id": "com.twitter.android:id/tweet_curation_action",
        "class": "android.widget.ImageView",
        "package": "com.twitter.android",
        "content-desc": "",
        "checkable": false,
        "checked": false,
        "clickable": true,
        "enabled": true,
        "focusable": true,
        "focused": false,
        "scrollable": false,
        "long-clickable": false,
        "password": false,
        "selected": false,
        "bounds": [
            981,
            1770,
            1069,
            1858
        ],
        "id": 69,
        "leaf-id": 37,
        "caption": "more options",
        "icon-cls": "more",
        "description": "more"
    },
    {
        "text": "",
        "resource-id": "com.twitter.android:id/tweet_content_text",
        "class": "android.view.View",
        "package": "com.twitter.android",
        "content-desc": "",
        "checkable": false,
        "checked": false,
        "clickable": true,
        "enabled": true,
        "focusable": true,
        "focused": false,
        "scrollable": false,
        "long-clickable": false,
        "password": false,
        "selected": false,
        "bounds": [
            210,
            1846,
            1047,
            2214
        ],
        "id": 70,
        "children-id": [
            71
        ]
    },
    {
        "text": "The 3 camps after $TSLA Investor Day\n\n1) asleep, not interested in engineering or the mission, just here for products and/or ST stock moves\n\n2) most of Wall St. - realizing they have no idea how to model any of what was just said, internally questioning career adequacy\n\n3)\u2026 Show more",
        "resource-id": "",
        "class": "android.view.View",
        "package": "com.twitter.android",
        "content-desc": "",
        "checkable": false,
        "checked": false,
        "clickable": true,
        "enabled": true,
        "focusable": true,
        "focused": false,
        "scrollable": false,
        "long-clickable": false,
        "password": false,
        "selected": false,
        "bounds": [
            210,
            1846,
            1047,
            2214
        ],
        "id": 71,
        "leaf-id": 38,
        "caption": "thumbnail",
        "icon-cls": null,
        "description": "The 3 camps after $TSLA Investor Day\n\n1) asleep, not interested in engineering or the mission, just here for products and/or ST stock moves\n\n2) most of Wall St. - realizing they have no idea how to model any of what was just said, internally questioning career adequacy\n\n3)\u2026 Show more"
    },
    {
        "text": "",
        "resource-id": "",
        "class": "android.view.ViewGroup",
        "package": "com.twitter.android",
        "content-desc": "",
        "checkable": false,
        "checked": false,
        "clickable": false,
        "enabled": true,
        "focusable": false,
        "focused": false,
        "scrollable": false,
        "long-clickable": false,
        "password": false,
        "selected": false,
        "bounds": [
            882,
            1862,
            1080,
            2060
        ],
        "id": 72,
        "children-id": [
            73
        ]
    },
    {
        "text": "",
        "resource-id": "com.twitter.android:id/composer_write",
        "class": "android.widget.ImageButton",
        "package": "com.twitter.android",
        "content-desc": "New Tweet",
        "checkable": false,
        "checked": false,
        "clickable": true,
        "enabled": true,
        "focusable": true,
        "focused": false,
        "scrollable": false,
        "long-clickable": false,
        "password": false,
        "selected": false,
        "bounds": [
            882,
            1862,
            1036,
            2016
        ],
        "id": 73,
        "leaf-id": 39,
        "caption": "add an entry",
        "icon-cls": "add",
        "description": "New Tweet"
    },
    {
        "text": "",
        "resource-id": "com.twitter.android:id/tabs",
        "class": "android.widget.HorizontalScrollView",
        "package": "com.twitter.android",
        "content-desc": "",
        "checkable": false,
        "checked": false,
        "clickable": false,
        "enabled": true,
        "focusable": true,
        "focused": false,
        "scrollable": false,
        "long-clickable": false,
        "password": false,
        "selected": false,
        "bounds": [
            0,
            2060,
            1080,
            2214
        ],
        "id": 74,
        "children-id": [
            75,
            76,
            78,
            80,
            82
        ]
    },
    {
        "text": "",
        "resource-id": "com.twitter.android:id/channels",
        "class": "android.view.View",
        "package": "com.twitter.android",
        "content-desc": "",
        "checkable": false,
        "checked": false,
        "clickable": false,
        "enabled": true,
        "focusable": false,
        "focused": false,
        "scrollable": false,
        "long-clickable": false,
        "password": false,
        "selected": true,
        "bounds": [
            33,
            2060,
            183,
            2214
        ],
        "id": 75,
        "leaf-id": 40,
        "caption": "<unk>",
        "icon-cls": null,
        "description": null
    },
    {
        "text": "",
        "resource-id": "",
        "class": "android.widget.LinearLayout",
        "package": "com.twitter.android",
        "content-desc": "Search and Explore",
        "checkable": false,
        "checked": false,
        "clickable": true,
        "enabled": true,
        "focusable": true,
        "focused": false,
        "scrollable": false,
        "long-clickable": false,
        "password": false,
        "selected": false,
        "bounds": [
            216,
            2060,
            432,
            2214
        ],
        "id": 76,
        "children-id": [
            77
        ]
    },
    {
        "text": "",
        "resource-id": "",
        "class": "android.view.View",
        "package": "com.twitter.android",
        "content-desc": "",
        "checkable": false,
        "checked": false,
        "clickable": true,
        "enabled": true,
        "focusable": false,
        "focused": false,
        "scrollable": false,
        "long-clickable": false,
        "password": false,
        "selected": false,
        "bounds": [
            249,
            2060,
            399,
            2214
        ],
        "id": 77,
        "leaf-id": 41,
        "caption": "search",
        "icon-cls": "search",
        "description": "search"
    },
    {
        "text": "",
        "resource-id": "",
        "class": "android.widget.LinearLayout",
        "package": "com.twitter.android",
        "content-desc": "Spaces",
        "checkable": false,
        "checked": false,
        "clickable": true,
        "enabled": true,
        "focusable": true,
        "focused": false,
        "scrollable": false,
        "long-clickable": false,
        "password": false,
        "selected": false,
        "bounds": [
            432,
            2060,
            648,
            2214
        ],
        "id": 78,
        "children-id": [
            79
        ]
    },
    {
        "text": "",
        "resource-id": "com.twitter.android:id/spaces",
        "class": "android.view.View",
        "package": "com.twitter.android",
        "content-desc": "",
        "checkable": false,
        "checked": false,
        "clickable": true,
        "enabled": true,
        "focusable": false,
        "focused": false,
        "scrollable": false,
        "long-clickable": false,
        "password": false,
        "selected": false,
        "bounds": [
            465,
            2060,
            615,
            2214
        ],
        "id": 79,
        "leaf-id": 42,
        "caption": "<unk>",
        "icon-cls": null,
        "description": null
    },
    {
        "text": "",
        "resource-id": "",
        "class": "android.widget.LinearLayout",
        "package": "com.twitter.android",
        "content-desc": "Notifications",
        "checkable": false,
        "checked": false,
        "clickable": true,
        "enabled": true,
        "focusable": true,
        "focused": false,
        "scrollable": false,
        "long-clickable": false,
        "password": false,
        "selected": false,
        "bounds": [
            648,
            2060,
            864,
            2214
        ],
        "id": 80,
        "children-id": [
            81
        ]
    },
    {
        "text": "",
        "resource-id": "com.twitter.android:id/notifications",
        "class": "android.view.View",
        "package": "com.twitter.android",
        "content-desc": "",
        "checkable": false,
        "checked": false,
        "clickable": true,
        "enabled": true,
        "focusable": false,
        "focused": false,
        "scrollable": false,
        "long-clickable": false,
        "password": false,
        "selected": false,
        "bounds": [
            681,
            2060,
            831,
            2214
        ],
        "id": 81,
        "leaf-id": 43,
        "caption": "<unk>",
        "icon-cls": "notifications",
        "description": "notifications"
    },
    {
        "text": "",
        "resource-id": "",
        "class": "android.widget.LinearLayout",
        "package": "com.twitter.android",
        "content-desc": "Messages",
        "checkable": false,
        "checked": false,
        "clickable": true,
        "enabled": true,
        "focusable": true,
        "focused": false,
        "scrollable": false,
        "long-clickable": false,
        "password": false,
        "selected": false,
        "bounds": [
            864,
            2060,
            1080,
            2214
        ],
        "id": 82,
        "children-id": [
            83
        ]
    },
    {
        "text": "",
        "resource-id": "com.twitter.android:id/dms",
        "class": "android.view.View",
        "package": "com.twitter.android",
        "content-desc": "",
        "checkable": false,
        "checked": false,
        "clickable": true,
        "enabled": true,
        "focusable": false,
        "focused": false,
        "scrollable": false,
        "long-clickable": false,
        "password": false,
        "selected": false,
        "bounds": [
            897,
            2060,
            1047,
            2214
        ],
        "id": 83,
        "leaf-id": 44,
        "caption": "<unk>",
        "icon-cls": "email",
        "description": "email"
    },
    {
        "text": "",
        "resource-id": "android:id/statusBarBackground",
        "class": "android.view.View",
        "package": "com.twitter.android",
        "content-desc": "",
        "checkable": false,
        "checked": false,
        "clickable": false,
        "enabled": true,
        "focusable": false,
        "focused": false,
        "scrollable": false,
        "long-clickable": false,
        "password": false,
        "selected": false,
        "bounds": [
            0,
            0,
            1080,
            66
        ],
        "id": 84,
        "leaf-id": 45,
        "caption": "<unk>",
        "icon-cls": null,
        "description": null
    }
]